odoo8_addon_l10n_it_fiscalcode-8.0.0.1.2-nspkg.pth
odoo_addons/l10n_it_fiscalcode/AUTHORS.txt
odoo_addons/l10n_it_fiscalcode/__init__.py
odoo_addons/l10n_it_fiscalcode/__openerp__.py
odoo_addons/l10n_it_fiscalcode/data/res.city.it.code.csv
odoo_addons/l10n_it_fiscalcode/i18n/es.po
odoo_addons/l10n_it_fiscalcode/i18n/it.po
odoo_addons/l10n_it_fiscalcode/i18n/l10n_it_fiscalcode.pot
odoo_addons/l10n_it_fiscalcode/i18n/sl.po
odoo_addons/l10n_it_fiscalcode/model/__init__.py
odoo_addons/l10n_it_fiscalcode/model/res_city_it_code.py
odoo_addons/l10n_it_fiscalcode/model/res_partner.py
odoo_addons/l10n_it_fiscalcode/security/ir.model.access.csv
odoo_addons/l10n_it_fiscalcode/static/description/icon.png
odoo_addons/l10n_it_fiscalcode/test/fiscalcode.yml
odoo_addons/l10n_it_fiscalcode/view/fiscalcode_view.xml
odoo_addons/l10n_it_fiscalcode/wizard/__init__.py
odoo_addons/l10n_it_fiscalcode/wizard/compute_fc.py
odoo_addons/l10n_it_fiscalcode/wizard/compute_fc_view.xml
odoo8_addon_l10n_it_fiscalcode-8.0.0.1.2.dist-info/METADATA
odoo8_addon_l10n_it_fiscalcode-8.0.0.1.2.dist-info/WHEEL
odoo8_addon_l10n_it_fiscalcode-8.0.0.1.2.dist-info/namespace_packages.txt
odoo8_addon_l10n_it_fiscalcode-8.0.0.1.2.dist-info/top_level.txt
odoo8_addon_l10n_it_fiscalcode-8.0.0.1.2.dist-info/RECORD
