Metadata-Version: 2.1
Name: odoo8-addon-l10n-it-fiscalcode
Version: 8.0.0.1.2
Summary: Italian Localisation - Fiscal Code
Home-page: http://www.odoo-italia.org
Author: Odoo Italian Community,Odoo Community Association (OCA)
Author-email: support@odoo-community.org
License: AGPL-3
Platform: UNKNOWN
Classifier: Programming Language :: Python
Classifier: Framework :: Odoo
Classifier: License :: OSI Approved :: GNU Affero General Public License v3
Requires-Python: ~=2.7
Requires-Dist: codicefiscale
Requires-Dist: odoo (<9.0a,>=8.0a)
